{
  "table": {
    "name": "UniverseDifficulty",
    "rows": [
      {
        "values": {
          "difficulty": {
            "Integer": 1
          },
          "id": {
            "Integer": 2
          },
          "kind": {
            "String": "Tutorial"
          },
          "recommended_elements": {
            "List": [
              {
                "String": "Ice"
              }
            ]
          },
          "recommended_level": {
            "Integer": 5
          },
          "score_curve_json": {
            "String": "[{\"score\":\"3600\",\"tier\":3}]"
          },
          "source_area_id": {
            "String": "100"
          },
          "stable_key": {
            "String": "universe.world.01.difficulty.tutorial"
          },
          "unlock_source_id": "Null",
          "world_id": {
            "Integer": 1
          }
        }
      },
      {
        "values": {
          "difficulty": {
            "Integer": 1
          },
          "id": {
            "Integer": 1
          },
          "kind": {
            "String": "Standard"
          },
          "recommended_elements": {
            "List": [
              {
                "String": "Quantum"
              },
              {
                "String": "Physical"
              },
              {
                "String": "Wind"
              }
            ]
          },
          "recommended_level": {
            "Integer": 14
          },
          "score_curve_json": {
            "String": "[{\"score\":\"260\",\"tier\":1},{\"score\":\"780\",\"tier\":2},{\"score\":\"780\",\"tier\":3},{\"score\":\"1300\",\"tier\":4},{\"score\":\"1560\",\"tier\":5},{\"score\":\"1560\",\"tier\":6},{\"score\":\"2600\",\"tier\":7}]"
          },
          "source_area_id": {
            "String": "110"
          },
          "stable_key": {
            "String": "universe.world.01.difficulty.01"
          },
          "unlock_source_id": {
            "String": "12001"
          },
          "world_id": {
            "Integer": 1
          }
        }
      },
      {
        "values": {
          "difficulty": {
            "Integer": 1
          },
          "id": {
            "Integer": 3
          },
          "kind": {
            "String": "Standard"
          },
          "recommended_elements": {
            "List": [
              {
                "String": "Thunder"
              },
              {
                "String": "Ice"
              }
            ]
          },
          "recommended_level": {
            "Integer": 25
          },
          "score_curve_json": {
            "String": "[{\"score\":\"180\",\"tier\":1},{\"score\":\"360\",\"tier\":2},{\"score\":\"540\",\"tier\":3},{\"score\":\"900\",\"tier\":4},{\"score\":\"900\",\"tier\":5},{\"score\":\"1260\",\"tier\":6},{\"score\":\"1440\",\"tier\":7},{\"score\":\"2160\",\"tier\":8},{\"score\":\"2160\",\"tier\":9},{\"score\":\"2520\",\"tier\":10},{\"score\":\"2880\",\"tier\":11},{\"score\":\"2880\",\"tier\":12},{\"score\":\"3600\",\"tier\":13}]"
          },
          "source_area_id": {
            "String": "120"
          },
          "stable_key": {
            "String": "universe.world.02.difficulty.01"
          },
          "unlock_source_id": {
            "String": "12002"
          },
          "world_id": {
            "Integer": 2
          }
        }
      },
      {
        "values": {
          "difficulty": {
            "Integer": 1
          },
          "id": {
            "Integer": 4
          },
          "kind": {
            "String": "Standard"
          },
          "recommended_elements": {
            "List": [
              {
                "String": "Physical"
              },
              {
                "String": "Thunder"
              },
              {
                "String": "Imaginary"
              }
            ]
          },
          "recommended_level": {
            "Integer": 30
          },
          "score_curve_json": {
            "String": "[{\"score\":\"300\",\"tier\":1},{\"score\":\"600\",\"tier\":2},{\"score\":\"900\",\"tier\":3},{\"score\":\"1500\",\"tier\":4},{\"score\":\"1500\",\"tier\":5},{\"score\":\"2100\",\"tier\":6},{\"score\":\"2400\",\"tier\":7},{\"score\":\"3300\",\"tier\":8},{\"score\":\"3300\",\"tier\":9},{\"score\":\"3900\",\"tier\":10},{\"score\":\"4500\",\"tier\":11},{\"score\":\"4500\",\"tier\":12},{\"score\":\"6000\",\"tier\":13}]"
          },
          "source_area_id": {
            "String": "130"
          },
          "stable_key": {
            "String": "universe.world.03.difficulty.01"
          },
          "unlock_source_id": {
            "String": "12003"
          },
          "world_id": {
            "Integer": 3
          }
        }
      },
      {
        "values": {
          "difficulty": {
            "Integer": 2
          },
          "id": {
            "Integer": 5
          },
          "kind": {
            "String": "Standard"
          },
          "recommended_elements": {
            "List": [
              {
                "String": "Physical"
              },
              {
                "String": "Thunder"
              },
              {
                "String": "Imaginary"
              }
            ]
          },
          "recommended_level": {
            "Integer": 62
          },
          "score_curve_json": {
            "String": "[{\"score\":\"400\",\"tier\":1},{\"score\":\"800\",\"tier\":2},{\"score\":\"1200\",\"tier\":3},{\"score\":\"2000\",\"tier\":4},{\"score\":\"2000\",\"tier\":5},{\"score\":\"2800\",\"tier\":6},{\"score\":\"3200\",\"tier\":7},{\"score\":\"4400\",\"tier\":8},{\"score\":\"4400\",\"tier\":9},{\"score\":\"5200\",\"tier\":10},{\"score\":\"6000\",\"tier\":11},{\"score\":\"6000\",\"tier\":12},{\"score\":\"8000\",\"tier\":13}]"
          },
          "source_area_id": {
            "String": "131"
          },
          "stable_key": {
            "String": "universe.world.03.difficulty.02"
          },
          "unlock_source_id": {
            "String": "12033"
          },
          "world_id": {
            "Integer": 3
          }
        }
      },
      {
        "values": {
          "difficulty": {
            "Integer": 3
          },
          "id": {
            "Integer": 6
          },
          "kind": {
            "String": "Standard"
          },
          "recommended_elements": {
            "List": [
              {
                "String": "Physical"
              },
              {
                "String": "Thunder"
              },
              {
                "String": "Imaginary"
              }
            ]
          },
          "recommended_level": {
            "Integer": 67
          },
          "score_curve_json": {
            "String": "[{\"score\":\"425\",\"tier\":1},{\"score\":\"850\",\"tier\":2},{\"score\":\"1275\",\"tier\":3},{\"score\":\"2125\",\"tier\":4},{\"score\":\"2125\",\"tier\":5},{\"score\":\"2975\",\"tier\":6},{\"score\":\"3400\",\"tier\":7},{\"score\":\"4675\",\"tier\":8},{\"score\":\"4675\",\"tier\":9},{\"score\":\"5525\",\"tier\":10},{\"score\":\"6375\",\"tier\":11},{\"score\":\"6375\",\"tier\":12},{\"score\":\"8500\",\"tier\":13}]"
          },
          "source_area_id": {
            "String": "132"
          },
          "stable_key": {
            "String": "universe.world.03.difficulty.03"
          },
          "unlock_source_id": {
            "String": "12034"
          },
          "world_id": {
            "Integer": 3
          }
        }
      },
      {
        "values": {
          "difficulty": {
            "Integer": 4
          },
          "id": {
            "Integer": 7
          },
          "kind": {
            "String": "Standard"
          },
          "recommended_elements": {
            "List": [
              {
                "String": "Physical"
              },
              {
                "String": "Thunder"
              },
              {
                "String": "Imaginary"
              }
            ]
          },
          "recommended_level": {
            "Integer": 76
          },
          "score_curve_json": {
            "String": "[{\"score\":\"450\",\"tier\":1},{\"score\":\"900\",\"tier\":2},{\"score\":\"1350\",\"tier\":3},{\"score\":\"2250\",\"tier\":4},{\"score\":\"2250\",\"tier\":5},{\"score\":\"3150\",\"tier\":6},{\"score\":\"3600\",\"tier\":7},{\"score\":\"4950\",\"tier\":8},{\"score\":\"4950\",\"tier\":9},{\"score\":\"5850\",\"tier\":10},{\"score\":\"6750\",\"tier\":11},{\"score\":\"6750\",\"tier\":12},{\"score\":\"9000\",\"tier\":13}]"
          },
          "source_area_id": {
            "String": "133"
          },
          "stable_key": {
            "String": "universe.world.03.difficulty.04"
          },
          "unlock_source_id": {
            "String": "12035"
          },
          "world_id": {
            "Integer": 3
          }
        }
      },
      {
        "values": {
          "difficulty": {
            "Integer": 5
          },
          "id": {
            "Integer": 8
          },
          "kind": {
            "String": "Standard"
          },
          "recommended_elements": {
            "List": [
              {
                "String": "Physical"
              },
              {
                "String": "Thunder"
              },
              {
                "String": "Imaginary"
              }
            ]
          },
          "recommended_level": {
            "Integer": 80
          },
          "score_curve_json": {
            "String": "[{\"score\":\"600\",\"tier\":1},{\"score\":\"1200\",\"tier\":2},{\"score\":\"1800\",\"tier\":3},{\"score\":\"3000\",\"tier\":4},{\"score\":\"3000\",\"tier\":5},{\"score\":\"4200\",\"tier\":6},{\"score\":\"4800\",\"tier\":7},{\"score\":\"6600\",\"tier\":8},{\"score\":\"6600\",\"tier\":9},{\"score\":\"7800\",\"tier\":10},{\"score\":\"9000\",\"tier\":11},{\"score\":\"9000\",\"tier\":12},{\"score\":\"12000\",\"tier\":13}]"
          },
          "source_area_id": {
            "String": "134"
          },
          "stable_key": {
            "String": "universe.world.03.difficulty.05"
          },
          "unlock_source_id": {
            "String": "12036"
          },
          "world_id": {
            "Integer": 3
          }
        }
      },
      {
        "values": {
          "difficulty": {
            "Integer": 1
          },
          "id": {
            "Integer": 9
          },
          "kind": {
            "String": "Standard"
          },
          "recommended_elements": {
            "List": [
              {
                "String": "Thunder"
              },
              {
                "String": "Wind"
              },
              {
                "String": "Fire"
              }
            ]
          },
          "recommended_level": {
            "Integer": 37
          },
          "score_curve_json": {
            "String": "[{\"score\":\"325\",\"tier\":1},{\"score\":\"650\",\"tier\":2},{\"score\":\"975\",\"tier\":3},{\"score\":\"1625\",\"tier\":4},{\"score\":\"1625\",\"tier\":5},{\"score\":\"2275\",\"tier\":6},{\"score\":\"2600\",\"tier\":7},{\"score\":\"3575\",\"tier\":8},{\"score\":\"3575\",\"tier\":9},{\"score\":\"4225\",\"tier\":10},{\"score\":\"4875\",\"tier\":11},{\"score\":\"4875\",\"tier\":12},{\"score\":\"6500\",\"tier\":13}]"
          },
          "source_area_id": {
            "String": "140"
          },
          "stable_key": {
            "String": "universe.world.04.difficulty.01"
          },
          "unlock_source_id": {
            "String": "12004"
          },
          "world_id": {
            "Integer": 4
          }
        }
      },
      {
        "values": {
          "difficulty": {
            "Integer": 2
          },
          "id": {
            "Integer": 10
          },
          "kind": {
            "String": "Standard"
          },
          "recommended_elements": {
            "List": [
              {
                "String": "Thunder"
              },
              {
                "String": "Wind"
              },
              {
                "String": "Fire"
              }
            ]
          },
          "recommended_level": {
            "Integer": 62
          },
          "score_curve_json": {
            "String": "[{\"score\":\"400\",\"tier\":1},{\"score\":\"800\",\"tier\":2},{\"score\":\"1200\",\"tier\":3},{\"score\":\"2000\",\"tier\":4},{\"score\":\"2000\",\"tier\":5},{\"score\":\"2800\",\"tier\":6},{\"score\":\"3200\",\"tier\":7},{\"score\":\"4400\",\"tier\":8},{\"score\":\"4400\",\"tier\":9},{\"score\":\"5200\",\"tier\":10},{\"score\":\"6000\",\"tier\":11},{\"score\":\"6000\",\"tier\":12},{\"score\":\"8000\",\"tier\":13}]"
          },
          "source_area_id": {
            "String": "141"
          },
          "stable_key": {
            "String": "universe.world.04.difficulty.02"
          },
          "unlock_source_id": {
            "String": "12011"
          },
          "world_id": {
            "Integer": 4
          }
        }
      },
      {
        "values": {
          "difficulty": {
            "Integer": 3
          },
          "id": {
            "Integer": 11
          },
          "kind": {
            "String": "Standard"
          },
          "recommended_elements": {
            "List": [
              {
                "String": "Thunder"
              },
              {
                "String": "Wind"
              },
              {
                "String": "Fire"
              }
            ]
          },
          "recommended_level": {
            "Integer": 67
          },
          "score_curve_json": {
            "String": "[{\"score\":\"425\",\"tier\":1},{\"score\":\"850\",\"tier\":2},{\"score\":\"1275\",\"tier\":3},{\"score\":\"2125\",\"tier\":4},{\"score\":\"2125\",\"tier\":5},{\"score\":\"2975\",\"tier\":6},{\"score\":\"3400\",\"tier\":7},{\"score\":\"4675\",\"tier\":8},{\"score\":\"4675\",\"tier\":9},{\"score\":\"5525\",\"tier\":10},{\"score\":\"6375\",\"tier\":11},{\"score\":\"6375\",\"tier\":12},{\"score\":\"8500\",\"tier\":13}]"
          },
          "source_area_id": {
            "String": "142"
          },
          "stable_key": {
            "String": "universe.world.04.difficulty.03"
          },
          "unlock_source_id": {
            "String": "12012"
          },
          "world_id": {
            "Integer": 4
          }
        }
      },
      {
        "values": {
          "difficulty": {
            "Integer": 4
          },
          "id": {
            "Integer": 12
          },
          "kind": {
            "String": "Standard"
          },
          "recommended_elements": {
            "List": [
              {
                "String": "Thunder"
              },
              {
                "String": "Wind"
              },
              {
                "String": "Fire"
              }
            ]
          },
          "recommended_level": {
            "Integer": 76
          },
          "score_curve_json": {
            "String": "[{\"score\":\"450\",\"tier\":1},{\"score\":\"900\",\"tier\":2},{\"score\":\"1350\",\"tier\":3},{\"score\":\"2250\",\"tier\":4},{\"score\":\"2250\",\"tier\":5},{\"score\":\"3150\",\"tier\":6},{\"score\":\"3600\",\"tier\":7},{\"score\":\"4950\",\"tier\":8},{\"score\":\"4950\",\"tier\":9},{\"score\":\"5850\",\"tier\":10},{\"score\":\"6750\",\"tier\":11},{\"score\":\"6750\",\"tier\":12},{\"score\":\"9000\",\"tier\":13}]"
          },
          "source_area_id": {
            "String": "143"
          },
          "stable_key": {
            "String": "universe.world.04.difficulty.04"
          },
          "unlock_source_id": {
            "String": "12013"
          },
          "world_id": {
            "Integer": 4
          }
        }
      },
      {
        "values": {
          "difficulty": {
            "Integer": 5
          },
          "id": {
            "Integer": 13
          },
          "kind": {
            "String": "Standard"
          },
          "recommended_elements": {
            "List": [
              {
                "String": "Thunder"
              },
              {
                "String": "Wind"
              },
              {
                "String": "Fire"
              }
            ]
          },
          "recommended_level": {
            "Integer": 80
          },
          "score_curve_json": {
            "String": "[{\"score\":\"600\",\"tier\":1},{\"score\":\"1200\",\"tier\":2},{\"score\":\"1800\",\"tier\":3},{\"score\":\"3000\",\"tier\":4},{\"score\":\"3000\",\"tier\":5},{\"score\":\"4200\",\"tier\":6},{\"score\":\"4800\",\"tier\":7},{\"score\":\"6600\",\"tier\":8},{\"score\":\"6600\",\"tier\":9},{\"score\":\"7800\",\"tier\":10},{\"score\":\"9000\",\"tier\":11},{\"score\":\"9000\",\"tier\":12},{\"score\":\"12000\",\"tier\":13}]"
          },
          "source_area_id": {
            "String": "144"
          },
          "stable_key": {
            "String": "universe.world.04.difficulty.05"
          },
          "unlock_source_id": {
            "String": "12014"
          },
          "world_id": {
            "Integer": 4
          }
        }
      },
      {
        "values": {
          "difficulty": {
            "Integer": 1
          },
          "id": {
            "Integer": 14
          },
          "kind": {
            "String": "Standard"
          },
          "recommended_elements": {
            "List": [
              {
                "String": "Wind"
              },
              {
                "String": "Imaginary"
              },
              {
                "String": "Physical"
              }
            ]
          },
          "recommended_level": {
            "Integer": 45
          },
          "score_curve_json": {
            "String": "[{\"score\":\"350\",\"tier\":1},{\"score\":\"700\",\"tier\":2},{\"score\":\"1050\",\"tier\":3},{\"score\":\"1750\",\"tier\":4},{\"score\":\"1750\",\"tier\":5},{\"score\":\"2450\",\"tier\":6},{\"score\":\"2800\",\"tier\":7},{\"score\":\"3850\",\"tier\":8},{\"score\":\"3850\",\"tier\":9},{\"score\":\"4550\",\"tier\":10},{\"score\":\"5250\",\"tier\":11},{\"score\":\"5250\",\"tier\":12},{\"score\":\"7000\",\"tier\":13}]"
          },
          "source_area_id": {
            "String": "150"
          },
          "stable_key": {
            "String": "universe.world.05.difficulty.01"
          },
          "unlock_source_id": {
            "String": "12005"
          },
          "world_id": {
            "Integer": 5
          }
        }
      },
      {
        "values": {
          "difficulty": {
            "Integer": 2
          },
          "id": {
            "Integer": 15
          },
          "kind": {
            "String": "Standard"
          },
          "recommended_elements": {
            "List": [
              {
                "String": "Wind"
              },
              {
                "String": "Imaginary"
              },
              {
                "String": "Physical"
              }
            ]
          },
          "recommended_level": {
            "Integer": 67
          },
          "score_curve_json": {
            "String": "[{\"score\":\"425\",\"tier\":1},{\"score\":\"850\",\"tier\":2},{\"score\":\"1275\",\"tier\":3},{\"score\":\"2125\",\"tier\":4},{\"score\":\"2125\",\"tier\":5},{\"score\":\"2975\",\"tier\":6},{\"score\":\"3400\",\"tier\":7},{\"score\":\"4675\",\"tier\":8},{\"score\":\"4675\",\"tier\":9},{\"score\":\"5525\",\"tier\":10},{\"score\":\"6375\",\"tier\":11},{\"score\":\"6375\",\"tier\":12},{\"score\":\"8500\",\"tier\":13}]"
          },
          "source_area_id": {
            "String": "151"
          },
          "stable_key": {
            "String": "universe.world.05.difficulty.02"
          },
          "unlock_source_id": {
            "String": "12015"
          },
          "world_id": {
            "Integer": 5
          }
        }
      },
      {
        "values": {
          "difficulty": {
            "Integer": 3
          },
          "id": {
            "Integer": 16
          },
          "kind": {
            "String": "Standard"
          },
          "recommended_elements": {
            "List": [
              {
                "String": "Wind"
              },
              {
                "String": "Imaginary"
              },
              {
                "String": "Physical"
              }
            ]
          },
          "recommended_level": {
            "Integer": 76
          },
          "score_curve_json": {
            "String": "[{\"score\":\"450\",\"tier\":1},{\"score\":\"900\",\"tier\":2},{\"score\":\"1350\",\"tier\":3},{\"score\":\"2250\",\"tier\":4},{\"score\":\"2250\",\"tier\":5},{\"score\":\"3150\",\"tier\":6},{\"score\":\"3600\",\"tier\":7},{\"score\":\"4950\",\"tier\":8},{\"score\":\"4950\",\"tier\":9},{\"score\":\"5850\",\"tier\":10},{\"score\":\"6750\",\"tier\":11},{\"score\":\"6750\",\"tier\":12},{\"score\":\"9000\",\"tier\":13}]"
          },
          "source_area_id": {
            "String": "152"
          },
          "stable_key": {
            "String": "universe.world.05.difficulty.03"
          },
          "unlock_source_id": {
            "String": "12016"
          },
          "world_id": {
            "Integer": 5
          }
        }
      },
      {
        "values": {
          "difficulty": {
            "Integer": 4
          },
          "id": {
            "Integer": 17
          },
          "kind": {
            "String": "Standard"
          },
          "recommended_elements": {
            "List": [
              {
                "String": "Wind"
              },
              {
                "String": "Imaginary"
              },
              {
                "String": "Physical"
              }
            ]
          },
          "recommended_level": {
            "Integer": 80
          },
          "score_curve_json": {
            "String": "[{\"score\":\"600\",\"tier\":1},{\"score\":\"1200\",\"tier\":2},{\"score\":\"1800\",\"tier\":3},{\"score\":\"3000\",\"tier\":4},{\"score\":\"3000\",\"tier\":5},{\"score\":\"4200\",\"tier\":6},{\"score\":\"4800\",\"tier\":7},{\"score\":\"6600\",\"tier\":8},{\"score\":\"6600\",\"tier\":9},{\"score\":\"7800\",\"tier\":10},{\"score\":\"9000\",\"tier\":11},{\"score\":\"9000\",\"tier\":12},{\"score\":\"12000\",\"tier\":13}]"
          },
          "source_area_id": {
            "String": "153"
          },
          "stable_key": {
            "String": "universe.world.05.difficulty.04"
          },
          "unlock_source_id": {
            "String": "12017"
          },
          "world_id": {
            "Integer": 5
          }
        }
      },
      {
        "values": {
          "difficulty": {
            "Integer": 1
          },
          "id": {
            "Integer": 18
          },
          "kind": {
            "String": "Standard"
          },
          "recommended_elements": {
            "List": [
              {
                "String": "Fire"
              },
              {
                "String": "Quantum"
              },
              {
                "String": "Thunder"
              }
            ]
          },
          "recommended_level": {
            "Integer": 50
          },
          "score_curve_json": {
            "String": "[{\"score\":\"400\",\"tier\":1},{\"score\":\"800\",\"tier\":2},{\"score\":\"1200\",\"tier\":3},{\"score\":\"2000\",\"tier\":4},{\"score\":\"2000\",\"tier\":5},{\"score\":\"2800\",\"tier\":6},{\"score\":\"3200\",\"tier\":7},{\"score\":\"4400\",\"tier\":8},{\"score\":\"4400\",\"tier\":9},{\"score\":\"5200\",\"tier\":10},{\"score\":\"6000\",\"tier\":11},{\"score\":\"6000\",\"tier\":12},{\"score\":\"8000\",\"tier\":13}]"
          },
          "source_area_id": {
            "String": "160"
          },
          "stable_key": {
            "String": "universe.world.06.difficulty.01"
          },
          "unlock_source_id": {
            "String": "12006"
          },
          "world_id": {
            "Integer": 6
          }
        }
      },
      {
        "values": {
          "difficulty": {
            "Integer": 2
          },
          "id": {
            "Integer": 19
          },
          "kind": {
            "String": "Standard"
          },
          "recommended_elements": {
            "List": [
              {
                "String": "Fire"
              },
              {
                "String": "Quantum"
              },
              {
                "String": "Thunder"
              }
            ]
          },
          "recommended_level": {
            "Integer": 67
          },
          "score_curve_json": {
            "String": "[{\"score\":\"425\",\"tier\":1},{\"score\":\"850\",\"tier\":2},{\"score\":\"1275\",\"tier\":3},{\"score\":\"2125\",\"tier\":4},{\"score\":\"2125\",\"tier\":5},{\"score\":\"2975\",\"tier\":6},{\"score\":\"3400\",\"tier\":7},{\"score\":\"4675\",\"tier\":8},{\"score\":\"4675\",\"tier\":9},{\"score\":\"5525\",\"tier\":10},{\"score\":\"6375\",\"tier\":11},{\"score\":\"6375\",\"tier\":12},{\"score\":\"8500\",\"tier\":13}]"
          },
          "source_area_id": {
            "String": "161"
          },
          "stable_key": {
            "String": "universe.world.06.difficulty.02"
          },
          "unlock_source_id": {
            "String": "12018"
          },
          "world_id": {
            "Integer": 6
          }
        }
      },
      {
        "values": {
          "difficulty": {
            "Integer": 3
          },
          "id": {
            "Integer": 20
          },
          "kind": {
            "String": "Standard"
          },
          "recommended_elements": {
            "List": [
              {
                "String": "Fire"
              },
              {
                "String": "Quantum"
              },
              {
                "String": "Thunder"
              }
            ]
          },
          "recommended_level": {
            "Integer": 76
          },
          "score_curve_json": {
            "String": "[{\"score\":\"450\",\"tier\":1},{\"score\":\"900\",\"tier\":2},{\"score\":\"1350\",\"tier\":3},{\"score\":\"2250\",\"tier\":4},{\"score\":\"2250\",\"tier\":5},{\"score\":\"3150\",\"tier\":6},{\"score\":\"3600\",\"tier\":7},{\"score\":\"4950\",\"tier\":8},{\"score\":\"4950\",\"tier\":9},{\"score\":\"5850\",\"tier\":10},{\"score\":\"6750\",\"tier\":11},{\"score\":\"6750\",\"tier\":12},{\"score\":\"9000\",\"tier\":13}]"
          },
          "source_area_id": {
            "String": "162"
          },
          "stable_key": {
            "String": "universe.world.06.difficulty.03"
          },
          "unlock_source_id": {
            "String": "12019"
          },
          "world_id": {
            "Integer": 6
          }
        }
      },
      {
        "values": {
          "difficulty": {
            "Integer": 4
          },
          "id": {
            "Integer": 21
          },
          "kind": {
            "String": "Standard"
          },
          "recommended_elements": {
            "List": [
              {
                "String": "Fire"
              },
              {
                "String": "Quantum"
              },
              {
                "String": "Thunder"
              }
            ]
          },
          "recommended_level": {
            "Integer": 80
          },
          "score_curve_json": {
            "String": "[{\"score\":\"600\",\"tier\":1},{\"score\":\"1200\",\"tier\":2},{\"score\":\"1800\",\"tier\":3},{\"score\":\"3000\",\"tier\":4},{\"score\":\"3000\",\"tier\":5},{\"score\":\"4200\",\"tier\":6},{\"score\":\"4800\",\"tier\":7},{\"score\":\"6600\",\"tier\":8},{\"score\":\"6600\",\"tier\":9},{\"score\":\"7800\",\"tier\":10},{\"score\":\"9000\",\"tier\":11},{\"score\":\"9000\",\"tier\":12},{\"score\":\"12000\",\"tier\":13}]"
          },
          "source_area_id": {
            "String": "163"
          },
          "stable_key": {
            "String": "universe.world.06.difficulty.04"
          },
          "unlock_source_id": {
            "String": "12020"
          },
          "world_id": {
            "Integer": 6
          }
        }
      },
      {
        "values": {
          "difficulty": {
            "Integer": 1
          },
          "id": {
            "Integer": 22
          },
          "kind": {
            "String": "Standard"
          },
          "recommended_elements": {
            "List": [
              {
                "String": "Fire"
              },
              {
                "String": "Ice"
              },
              {
                "String": "Quantum"
              }
            ]
          },
          "recommended_level": {
            "Integer": 51
          },
          "score_curve_json": {
            "String": "[{\"score\":\"400\",\"tier\":1},{\"score\":\"800\",\"tier\":2},{\"score\":\"1200\",\"tier\":3},{\"score\":\"2000\",\"tier\":4},{\"score\":\"2000\",\"tier\":5},{\"score\":\"2800\",\"tier\":6},{\"score\":\"3200\",\"tier\":7},{\"score\":\"4400\",\"tier\":8},{\"score\":\"4400\",\"tier\":9},{\"score\":\"5200\",\"tier\":10},{\"score\":\"6000\",\"tier\":11},{\"score\":\"6000\",\"tier\":12},{\"score\":\"8000\",\"tier\":13}]"
          },
          "source_area_id": {
            "String": "170"
          },
          "stable_key": {
            "String": "universe.world.07.difficulty.01"
          },
          "unlock_source_id": {
            "String": "12021"
          },
          "world_id": {
            "Integer": 7
          }
        }
      },
      {
        "values": {
          "difficulty": {
            "Integer": 2
          },
          "id": {
            "Integer": 23
          },
          "kind": {
            "String": "Standard"
          },
          "recommended_elements": {
            "List": [
              {
                "String": "Fire"
              },
              {
                "String": "Ice"
              },
              {
                "String": "Quantum"
              }
            ]
          },
          "recommended_level": {
            "Integer": 67
          },
          "score_curve_json": {
            "String": "[{\"score\":\"425\",\"tier\":1},{\"score\":\"850\",\"tier\":2},{\"score\":\"1275\",\"tier\":3},{\"score\":\"2125\",\"tier\":4},{\"score\":\"2125\",\"tier\":5},{\"score\":\"2975\",\"tier\":6},{\"score\":\"3400\",\"tier\":7},{\"score\":\"4675\",\"tier\":8},{\"score\":\"4675\",\"tier\":9},{\"score\":\"5525\",\"tier\":10},{\"score\":\"6375\",\"tier\":11},{\"score\":\"6375\",\"tier\":12},{\"score\":\"8500\",\"tier\":13}]"
          },
          "source_area_id": {
            "String": "171"
          },
          "stable_key": {
            "String": "universe.world.07.difficulty.02"
          },
          "unlock_source_id": {
            "String": "12022"
          },
          "world_id": {
            "Integer": 7
          }
        }
      },
      {
        "values": {
          "difficulty": {
            "Integer": 3
          },
          "id": {
            "Integer": 24
          },
          "kind": {
            "String": "Standard"
          },
          "recommended_elements": {
            "List": [
              {
                "String": "Fire"
              },
              {
                "String": "Ice"
              },
              {
                "String": "Quantum"
              }
            ]
          },
          "recommended_level": {
            "Integer": 76
          },
          "score_curve_json": {
            "String": "[{\"score\":\"450\",\"tier\":1},{\"score\":\"900\",\"tier\":2},{\"score\":\"1350\",\"tier\":3},{\"score\":\"2250\",\"tier\":4},{\"score\":\"2250\",\"tier\":5},{\"score\":\"3150\",\"tier\":6},{\"score\":\"3600\",\"tier\":7},{\"score\":\"4950\",\"tier\":8},{\"score\":\"4950\",\"tier\":9},{\"score\":\"5850\",\"tier\":10},{\"score\":\"6750\",\"tier\":11},{\"score\":\"6750\",\"tier\":12},{\"score\":\"9000\",\"tier\":13}]"
          },
          "source_area_id": {
            "String": "172"
          },
          "stable_key": {
            "String": "universe.world.07.difficulty.03"
          },
          "unlock_source_id": {
            "String": "12023"
          },
          "world_id": {
            "Integer": 7
          }
        }
      },
      {
        "values": {
          "difficulty": {
            "Integer": 4
          },
          "id": {
            "Integer": 25
          },
          "kind": {
            "String": "Standard"
          },
          "recommended_elements": {
            "List": [
              {
                "String": "Fire"
              },
              {
                "String": "Ice"
              },
              {
                "String": "Quantum"
              }
            ]
          },
          "recommended_level": {
            "Integer": 80
          },
          "score_curve_json": {
            "String": "[{\"score\":\"600\",\"tier\":1},{\"score\":\"1200\",\"tier\":2},{\"score\":\"1800\",\"tier\":3},{\"score\":\"3000\",\"tier\":4},{\"score\":\"3000\",\"tier\":5},{\"score\":\"4200\",\"tier\":6},{\"score\":\"4800\",\"tier\":7},{\"score\":\"6600\",\"tier\":8},{\"score\":\"6600\",\"tier\":9},{\"score\":\"7800\",\"tier\":10},{\"score\":\"9000\",\"tier\":11},{\"score\":\"9000\",\"tier\":12},{\"score\":\"12000\",\"tier\":13}]"
          },
          "source_area_id": {
            "String": "173"
          },
          "stable_key": {
            "String": "universe.world.07.difficulty.04"
          },
          "unlock_source_id": {
            "String": "12024"
          },
          "world_id": {
            "Integer": 7
          }
        }
      },
      {
        "values": {
          "difficulty": {
            "Integer": 1
          },
          "id": {
            "Integer": 26
          },
          "kind": {
            "String": "Standard"
          },
          "recommended_elements": {
            "List": [
              {
                "String": "Thunder"
              },
              {
                "String": "Wind"
              },
              {
                "String": "Imaginary"
              }
            ]
          },
          "recommended_level": {
            "Integer": 51
          },
          "score_curve_json": {
            "String": "[{\"score\":\"400\",\"tier\":1},{\"score\":\"800\",\"tier\":2},{\"score\":\"1200\",\"tier\":3},{\"score\":\"2000\",\"tier\":4},{\"score\":\"2000\",\"tier\":5},{\"score\":\"2800\",\"tier\":6},{\"score\":\"3200\",\"tier\":7},{\"score\":\"4400\",\"tier\":8},{\"score\":\"4400\",\"tier\":9},{\"score\":\"5200\",\"tier\":10},{\"score\":\"6000\",\"tier\":11},{\"score\":\"6000\",\"tier\":12},{\"score\":\"8000\",\"tier\":13}]"
          },
          "source_area_id": {
            "String": "180"
          },
          "stable_key": {
            "String": "universe.world.08.difficulty.01"
          },
          "unlock_source_id": {
            "String": "12025"
          },
          "world_id": {
            "Integer": 8
          }
        }
      },
      {
        "values": {
          "difficulty": {
            "Integer": 2
          },
          "id": {
            "Integer": 27
          },
          "kind": {
            "String": "Standard"
          },
          "recommended_elements": {
            "List": [
              {
                "String": "Thunder"
              },
              {
                "String": "Wind"
              },
              {
                "String": "Imaginary"
              }
            ]
          },
          "recommended_level": {
            "Integer": 67
          },
          "score_curve_json": {
            "String": "[{\"score\":\"425\",\"tier\":1},{\"score\":\"850\",\"tier\":2},{\"score\":\"1275\",\"tier\":3},{\"score\":\"2125\",\"tier\":4},{\"score\":\"2125\",\"tier\":5},{\"score\":\"2975\",\"tier\":6},{\"score\":\"3400\",\"tier\":7},{\"score\":\"4675\",\"tier\":8},{\"score\":\"4675\",\"tier\":9},{\"score\":\"5525\",\"tier\":10},{\"score\":\"6375\",\"tier\":11},{\"score\":\"6375\",\"tier\":12},{\"score\":\"8500\",\"tier\":13}]"
          },
          "source_area_id": {
            "String": "181"
          },
          "stable_key": {
            "String": "universe.world.08.difficulty.02"
          },
          "unlock_source_id": {
            "String": "12026"
          },
          "world_id": {
            "Integer": 8
          }
        }
      },
      {
        "values": {
          "difficulty": {
            "Integer": 3
          },
          "id": {
            "Integer": 28
          },
          "kind": {
            "String": "Standard"
          },
          "recommended_elements": {
            "List": [
              {
                "String": "Thunder"
              },
              {
                "String": "Wind"
              },
              {
                "String": "Imaginary"
              }
            ]
          },
          "recommended_level": {
            "Integer": 76
          },
          "score_curve_json": {
            "String": "[{\"score\":\"450\",\"tier\":1},{\"score\":\"900\",\"tier\":2},{\"score\":\"1350\",\"tier\":3},{\"score\":\"2250\",\"tier\":4},{\"score\":\"2250\",\"tier\":5},{\"score\":\"3150\",\"tier\":6},{\"score\":\"3600\",\"tier\":7},{\"score\":\"4950\",\"tier\":8},{\"score\":\"4950\",\"tier\":9},{\"score\":\"5850\",\"tier\":10},{\"score\":\"6750\",\"tier\":11},{\"score\":\"6750\",\"tier\":12},{\"score\":\"9000\",\"tier\":13}]"
          },
          "source_area_id": {
            "String": "182"
          },
          "stable_key": {
            "String": "universe.world.08.difficulty.03"
          },
          "unlock_source_id": {
            "String": "12027"
          },
          "world_id": {
            "Integer": 8
          }
        }
      },
      {
        "values": {
          "difficulty": {
            "Integer": 4
          },
          "id": {
            "Integer": 29
          },
          "kind": {
            "String": "Standard"
          },
          "recommended_elements": {
            "List": [
              {
                "String": "Thunder"
              },
              {
                "String": "Wind"
              },
              {
                "String": "Imaginary"
              }
            ]
          },
          "recommended_level": {
            "Integer": 80
          },
          "score_curve_json": {
            "String": "[{\"score\":\"600\",\"tier\":1},{\"score\":\"1200\",\"tier\":2},{\"score\":\"1800\",\"tier\":3},{\"score\":\"3000\",\"tier\":4},{\"score\":\"3000\",\"tier\":5},{\"score\":\"4200\",\"tier\":6},{\"score\":\"4800\",\"tier\":7},{\"score\":\"6600\",\"tier\":8},{\"score\":\"6600\",\"tier\":9},{\"score\":\"7800\",\"tier\":10},{\"score\":\"9000\",\"tier\":11},{\"score\":\"9000\",\"tier\":12},{\"score\":\"12000\",\"tier\":13}]"
          },
          "source_area_id": {
            "String": "183"
          },
          "stable_key": {
            "String": "universe.world.08.difficulty.04"
          },
          "unlock_source_id": {
            "String": "12028"
          },
          "world_id": {
            "Integer": 8
          }
        }
      },
      {
        "values": {
          "difficulty": {
            "Integer": 1
          },
          "id": {
            "Integer": 30
          },
          "kind": {
            "String": "Standard"
          },
          "recommended_elements": {
            "List": [
              {
                "String": "Fire"
              },
              {
                "String": "Wind"
              },
              {
                "String": "Imaginary"
              }
            ]
          },
          "recommended_level": {
            "Integer": 51
          },
          "score_curve_json": {
            "String": "[{\"score\":\"400\",\"tier\":1},{\"score\":\"800\",\"tier\":2},{\"score\":\"1200\",\"tier\":3},{\"score\":\"2000\",\"tier\":4},{\"score\":\"2000\",\"tier\":5},{\"score\":\"2800\",\"tier\":6},{\"score\":\"3200\",\"tier\":7},{\"score\":\"4400\",\"tier\":8},{\"score\":\"4400\",\"tier\":9},{\"score\":\"5200\",\"tier\":10},{\"score\":\"6000\",\"tier\":11},{\"score\":\"6000\",\"tier\":12},{\"score\":\"8000\",\"tier\":13}]"
          },
          "source_area_id": {
            "String": "190"
          },
          "stable_key": {
            "String": "universe.world.09.difficulty.01"
          },
          "unlock_source_id": {
            "String": "12029"
          },
          "world_id": {
            "Integer": 9
          }
        }
      },
      {
        "values": {
          "difficulty": {
            "Integer": 2
          },
          "id": {
            "Integer": 31
          },
          "kind": {
            "String": "Standard"
          },
          "recommended_elements": {
            "List": [
              {
                "String": "Fire"
              },
              {
                "String": "Wind"
              },
              {
                "String": "Imaginary"
              }
            ]
          },
          "recommended_level": {
            "Integer": 67
          },
          "score_curve_json": {
            "String": "[{\"score\":\"425\",\"tier\":1},{\"score\":\"850\",\"tier\":2},{\"score\":\"1275\",\"tier\":3},{\"score\":\"2125\",\"tier\":4},{\"score\":\"2125\",\"tier\":5},{\"score\":\"2975\",\"tier\":6},{\"score\":\"3400\",\"tier\":7},{\"score\":\"4675\",\"tier\":8},{\"score\":\"4675\",\"tier\":9},{\"score\":\"5525\",\"tier\":10},{\"score\":\"6375\",\"tier\":11},{\"score\":\"6375\",\"tier\":12},{\"score\":\"8500\",\"tier\":13}]"
          },
          "source_area_id": {
            "String": "191"
          },
          "stable_key": {
            "String": "universe.world.09.difficulty.02"
          },
          "unlock_source_id": {
            "String": "12030"
          },
          "world_id": {
            "Integer": 9
          }
        }
      },
      {
        "values": {
          "difficulty": {
            "Integer": 3
          },
          "id": {
            "Integer": 32
          },
          "kind": {
            "String": "Standard"
          },
          "recommended_elements": {
            "List": [
              {
                "String": "Fire"
              },
              {
                "String": "Wind"
              },
              {
                "String": "Imaginary"
              }
            ]
          },
          "recommended_level": {
            "Integer": 76
          },
          "score_curve_json": {
            "String": "[{\"score\":\"450\",\"tier\":1},{\"score\":\"900\",\"tier\":2},{\"score\":\"1350\",\"tier\":3},{\"score\":\"2250\",\"tier\":4},{\"score\":\"2250\",\"tier\":5},{\"score\":\"3150\",\"tier\":6},{\"score\":\"3600\",\"tier\":7},{\"score\":\"4950\",\"tier\":8},{\"score\":\"4950\",\"tier\":9},{\"score\":\"5850\",\"tier\":10},{\"score\":\"6750\",\"tier\":11},{\"score\":\"6750\",\"tier\":12},{\"score\":\"9000\",\"tier\":13}]"
          },
          "source_area_id": {
            "String": "192"
          },
          "stable_key": {
            "String": "universe.world.09.difficulty.03"
          },
          "unlock_source_id": {
            "String": "12031"
          },
          "world_id": {
            "Integer": 9
          }
        }
      },
      {
        "values": {
          "difficulty": {
            "Integer": 4
          },
          "id": {
            "Integer": 33
          },
          "kind": {
            "String": "Standard"
          },
          "recommended_elements": {
            "List": [
              {
                "String": "Fire"
              },
              {
                "String": "Wind"
              },
              {
                "String": "Imaginary"
              }
            ]
          },
          "recommended_level": {
            "Integer": 80
          },
          "score_curve_json": {
            "String": "[{\"score\":\"600\",\"tier\":1},{\"score\":\"1200\",\"tier\":2},{\"score\":\"1800\",\"tier\":3},{\"score\":\"3000\",\"tier\":4},{\"score\":\"3000\",\"tier\":5},{\"score\":\"4200\",\"tier\":6},{\"score\":\"4800\",\"tier\":7},{\"score\":\"6600\",\"tier\":8},{\"score\":\"6600\",\"tier\":9},{\"score\":\"7800\",\"tier\":10},{\"score\":\"9000\",\"tier\":11},{\"score\":\"9000\",\"tier\":12},{\"score\":\"12000\",\"tier\":13}]"
          },
          "source_area_id": {
            "String": "193"
          },
          "stable_key": {
            "String": "universe.world.09.difficulty.04"
          },
          "unlock_source_id": {
            "String": "12032"
          },
          "world_id": {
            "Integer": 9
          }
        }
      }
    ]
  }
}